{
  "run_id": "run_20250911_234215",
  "timestamp": "2025-09-11T23:42:19.062027",
  "mod_name": "Nep_Local_Knowledge",
  "mod_id": "3511535258",
  "status": "baseline",
  "added_count": 10,
  "added_keys": [
    "Sandbox_AlwaysKnowRoads",
    "Sandbox_AlwaysKnowRoads_tooltip",
    "Sandbox_NLKMinWidth",
    "Sandbox_NLKMinWidth_tooltip",
    "Sandbox_NLKNRoadAtlas",
    "Sandbox_NLKNRoadAtlas_tooltip",
    "Sandbox_NLKPercentRevealed",
    "Sandbox_NLKPercentRevealed_tooltip",
    "Sandbox_NLKXXXXXX",
    "Sandbox_NLKXXXXXX_tooltip"
  ]
}